payloadinspector/__init__.py
payloadinspector/main.py
payloadinspector/payloadinspector.py
payloadinspector-1.0.1.dist-info/LICENSE
payloadinspector-1.0.1.dist-info/METADATA
payloadinspector-1.0.1.dist-info/WHEEL
payloadinspector-1.0.1.dist-info/entry_points.txt
payloadinspector-1.0.1.dist-info/top_level.txt
payloadinspector-1.0.1.dist-info/RECORD
