Metadata-Version: 2.2
Name: payloadinspector
Version: 1.0.1
Summary: Inspect byte strings as bit fields
Author-email: Fredrik Bakkevig Haugli <fredrik@haugli.org>
Project-URL: Homepage, https://gitlab.com/fredrikh/payloadinspector
Project-URL: Issues, https://gitlab.com/fredrikh/payloadinspector/-/issues
Classifier: Programming Language :: Python :: 3
Classifier: Operating System :: OS Independent
Requires-Python: >=3.9
License-File: LICENSE
